Metadata-Version: 2.1
Name: bubblemsg
Version: 3.0
Summary: 一个基于气泡窗而诞生的模块。
Home-page: https://www.bilibili.com/video/BV1GJ411x7h7
Download-URL: https://b23.tv/ltdukZY
Author: 小松果
Author-email: aaron.dongsq@hotmail.com
Maintainer: 小松果
Maintainer-email: aaron.dongsq@hotmail.com
License-File: LICENSE
